al_faraheedy/__init__.py
al_faraheedy/main.py
al_faraheedy_python-1.0.0.dist-info/METADATA
al_faraheedy_python-1.0.0.dist-info/WHEEL
al_faraheedy_python-1.0.0.dist-info/entry_points.txt
al_faraheedy_python-1.0.0.dist-info/top_level.txt
al_faraheedy_python-1.0.0.dist-info/RECORD
