Metadata-Version: 2.4
Name: al-faraheedy-python
Version: 1.0.0
Summary: Al Faraheedy Python: A Pythonized version of the Arabic Poetry Rhythm and Rhyme Analyzer Project
Home-page: https://github.com/muktarsayedsaleh/al-faraheedy-python
Author: Muktar Sayed Saleh
Author-email: Muktar Sayed Saleh <muktar@monjz.com>
Maintainer-email: Muktar Sayed Saleh <muktar@monjz.com>
Project-URL: Homepage, https://github.com/muktarsayedsaleh/al-faraheedy-python
Project-URL: Documentation, https://al-faraheedy-python.readthedocs.io/
Project-URL: Repository, https://github.com/muktarsayedsaleh/al-faraheedy-python
Project-URL: Bug Tracker, https://github.com/muktarsayedsaleh/al-faraheedy-python/issues
Project-URL: Original Project, http://www.faraheedy.com
Keywords: arabic,poetry,prosody,nlp,linguistics,meter,rhyme,عربي,شعر,عروض,قافية,بحر,faraheedy,farahidi,computational-linguistics,digital-humanities
Classifier: Development Status :: 5 - Production/Stable
Classifier: Intended Audience :: Developers
Classifier: Intended Audience :: Education
Classifier: Intended Audience :: Science/Research
Classifier: Topic :: Text Processing :: Linguistic
Classifier: Topic :: Scientific/Engineering :: Artificial Intelligence
Classifier: Topic :: Software Development :: Libraries :: Python Modules
Classifier: License :: OSI Approved :: MIT License
Classifier: Programming Language :: Python :: 3
Classifier: Programming Language :: Python :: 3.7
Classifier: Programming Language :: Python :: 3.8
Classifier: Programming Language :: Python :: 3.9
Classifier: Programming Language :: Python :: 3.10
Classifier: Programming Language :: Python :: 3.11
Classifier: Programming Language :: Python :: 3.12
Classifier: Operating System :: OS Independent
Classifier: Natural Language :: Arabic
Requires-Python: >=3.7
Provides-Extra: dev
Requires-Dist: pytest>=6.0; extra == "dev"
Requires-Dist: pytest-cov>=2.0; extra == "dev"
Requires-Dist: black>=21.0; extra == "dev"
Requires-Dist: isort>=5.0; extra == "dev"
Requires-Dist: flake8>=3.8; extra == "dev"
Requires-Dist: mypy>=0.800; extra == "dev"
Requires-Dist: pre-commit>=2.0; extra == "dev"
Provides-Extra: docs
Requires-Dist: sphinx>=4.0; extra == "docs"
Requires-Dist: sphinx-rtd-theme>=1.0; extra == "docs"
Requires-Dist: myst-parser>=0.18; extra == "docs"
Provides-Extra: cli
Requires-Dist: click>=8.0; extra == "cli"
Requires-Dist: rich>=10.0; extra == "cli"
Requires-Dist: typer>=0.6; extra == "cli"
Dynamic: author
Dynamic: home-page
Dynamic: requires-python
